pymacro/__init__.py
pymacro/pymacro.py
python_pymacro-0.1.0.dist-info/WHEEL
python_pymacro-0.1.0.dist-info/METADATA
python_pymacro-0.1.0.dist-info/RECORD
