Metadata-Version: 2.1
Name: python-pymacro
Version: 0.1.0
Summary: A python library that can be used to have macros inside python functions through decorators.
Home-page: https://github.com/AbooMinister25/pymacro
Author: AbooMinister25
Author-email: aboominister@gmail.com
Requires-Python: >=3.9,<4.0
Classifier: Programming Language :: Python :: 3
Classifier: Programming Language :: Python :: 3.9
Project-URL: Repository, https://github.com/AbooMinister25/pymacro
